martypy/ClientGeneric.py
martypy/ClientMV1.py
martypy/ClientMV2.py
martypy/Exceptions.py
martypy/LikeHDLC.py
martypy/Marty.py
martypy/ProtocolOverAscii.py
martypy/RICCommsBase.py
martypy/RICCommsParams.py
martypy/RICCommsSerial.py
martypy/RICCommsTest.py
martypy/RICCommsWiFi.py
martypy/RICHWElems.py
martypy/RICInterface.py
martypy/RICProtocols.py
martypy/RICROSSerial.py
martypy/RICStreamHandler.py
martypy/RateAverager.py
martypy/Text2Speech.py
martypy/ValueAverager.py
martypy/WebSocket.py
martypy/WebSocketFrame.py
martypy/__init__.py
martypy/tests/__init__.py
martypy/tests/testBaudRateSelection.py
martypy/tests/testColourSensor.py
martypy/tests/testStreamMP3.py
martypy/tests/test_martypy.py
martypy/tests/testrob.py
martypy-3.7.1.dist-info/LICENSE.md
martypy-3.7.1.dist-info/METADATA
martypy-3.7.1.dist-info/WHEEL
martypy-3.7.1.dist-info/top_level.txt
martypy-3.7.1.dist-info/RECORD
