Metadata-Version: 2.1
Name: martypy
Version: 3.7.1
Summary: Python library for Marty the Robot V1 and V2
Home-page: http://github.com/robotical/martypy
Author: Robotical
Author-email: hello@robotical.io
Maintainer: Robotical
Maintainer-email: hello@robotical.io
License: Apache 2.0
Keywords: ros,robot,marty,marty the robot,robotical
Classifier: Development Status :: 5 - Production/Stable
Classifier: Programming Language :: Python :: 3.4
Classifier: Programming Language :: Python :: 3.5
Classifier: Programming Language :: Python :: 3.6
Classifier: Programming Language :: Python :: 3.7
Classifier: Programming Language :: Python :: 3.8
Classifier: Operating System :: OS Independent
Classifier: License :: OSI Approved :: Apache Software License
License-File: LICENSE.md
Requires-Dist: pyserial
Requires-Dist: packaging
Requires-Dist: requests
Requires-Dist: pydub
Provides-Extra: tests
Requires-Dist: pytest; extra == "tests"
